vharfbuzz/__init__.py
vharfbuzz/_version.py
vharfbuzz-0.3.1.dist-info/LICENSE
vharfbuzz-0.3.1.dist-info/METADATA
vharfbuzz-0.3.1.dist-info/WHEEL
vharfbuzz-0.3.1.dist-info/top_level.txt
vharfbuzz-0.3.1.dist-info/RECORD
