Metadata-Version: 2.1
Name: vharfbuzz
Version: 0.3.1
Summary: A user-friendlier way to use Harfbuzz in Python
Author-email: Simon Cozens <simon@simon-cozens.org>
License: MIT License
Project-URL: Repository, https://github.com/simoncozens/vharfbuzz
Project-URL: Issues, https://github.com/simoncozens/vharfbuzz/issues
Classifier: Environment :: Console
Classifier: Topic :: Text Processing :: Fonts
License-File: LICENSE
Requires-Dist: uharfbuzz>=0.34.0
Requires-Dist: fontTools
Provides-Extra: dev
Requires-Dist: pytest; extra == "dev"
Requires-Dist: black; extra == "dev"
